opslib/mysql/__init__.py
ops_lib_mysql-1.0.dist-info/LICENSE
ops_lib_mysql-1.0.dist-info/METADATA
ops_lib_mysql-1.0.dist-info/WHEEL
ops_lib_mysql-1.0.dist-info/top_level.txt
ops_lib_mysql-1.0.dist-info/RECORD
