Metadata-Version: 2.1
Name: ops-lib-mysql
Version: 1.0
Summary: MySQL database relation for Juju Operator Framework Charms
Home-page: https://github.com/canonical/ops-lib-mysql
Author: Stuart Bishop
Author-email: stuart.bishop@canonical.com
Maintainer: Canonical
License: UNKNOWN
Project-URL: Juju, https://juju.is/
Project-URL: Juju Operator Framework, https://pypi.org/project/ops/
Keywords: juju charm opslib mysql mariadb
Platform: UNKNOWN
Classifier: Development Status :: 5 - Production/Stable
Classifier: Programming Language :: Python :: 3 :: Only
Classifier: Programming Language :: Python :: 3.6
Classifier: Programming Language :: Python :: 3.7
Classifier: Programming Language :: Python :: 3.8
Classifier: Programming Language :: Python :: 3.9
Classifier: License :: OSI Approved :: GNU Lesser General Public License v3 (LGPLv3)
Classifier: Operating System :: OS Independent
Requires-Python: >=3.6
Requires-Dist: ops (>=0.8.0)
